alert_exporter/__init__.py
alert_exporter/__main__.py
alert_exporter/cli.py
alert_exporter/sources/__init__.py
alert_exporter/sources/cloudwatch.py
alert_exporter/sources/kubernetes.py
alert_exporter/sources/pingdom.py
alert_exporter/templates/alerts.html.jinja
alert_exporter/templates/alerts.md.jinja
alert_exporter/templates/alerts.yaml.jinja
alert_exporter-0.5.1.dist-info/LICENSE
alert_exporter-0.5.1.dist-info/METADATA
alert_exporter-0.5.1.dist-info/WHEEL
alert_exporter-0.5.1.dist-info/entry_points.txt
alert_exporter-0.5.1.dist-info/top_level.txt
alert_exporter-0.5.1.dist-info/RECORD
