Metadata-Version: 2.1
Name: alert-exporter
Version: 0.5.1
Summary: Extract alerts configured in different sources (eg: Prometheus Rules, CloudWatch Alarms, Pingdom)
Author-email: Baptiste ROUX <rouxbaptiste@outlook.com>
License: GNU GENERAL PUBLIC LICENSE
Project-URL: Homepage, https://github.com/BapRx/alert-exporter
Project-URL: Bug Tracker, https://github.com/BapRx/alert-exporter/issues
Project-URL: changelog, https://github.com/BapRx/alert-exporter/blob/master/CHANGELOG.md
Keywords: alert_exporter,alert,monitoring,prometheus,cloudwatch
Classifier: Development Status :: 4 - Beta
Classifier: Programming Language :: Python :: 3
Classifier: Programming Language :: Python :: 3 :: Only
Requires-Python: >=3.7
License-File: LICENSE
Requires-Dist: kubernetes
Requires-Dist: boto3
Requires-Dist: humanize
Requires-Dist: jinja2
